ssb_libtest74/__init__.py
ssb_libtest74/__main__.py
ssb_libtest74/functions.py
ssb_libtest74/py.typed
ssb_libtest74-0.0.1.dist-info/LICENSE
ssb_libtest74-0.0.1.dist-info/METADATA
ssb_libtest74-0.0.1.dist-info/WHEEL
ssb_libtest74-0.0.1.dist-info/entry_points.txt
ssb_libtest74-0.0.1.dist-info/RECORD
